lib/__init__.py
lib/libturbojpeg/__init__.py
lib/libturbojpeg/lib32/__init__.py
lib/libturbojpeg/lib32/libturbojpeg.so.0
sic_framework/__init__.py
sic_framework/core/__init__.py
sic_framework/core/actuator_python2.py
sic_framework/core/component_manager_python2.py
sic_framework/core/component_python2.py
sic_framework/core/connector.py
sic_framework/core/message_python2.py
sic_framework/core/sensor_python2.py
sic_framework/core/service.py
sic_framework/core/service_python2.py
sic_framework/core/sic_application.py
sic_framework/core/sic_logging.py
sic_framework/core/sic_redis.py
sic_framework/core/utils.py
sic_framework/core/utils_cv2.py
sic_framework/devices/__init__.py
sic_framework/devices/alphamini.py
sic_framework/devices/desktop.py
sic_framework/devices/device.py
sic_framework/devices/franka.py
sic_framework/devices/nao.py
sic_framework/devices/nao_stub.py
sic_framework/devices/naoqi_shared.py
sic_framework/devices/pepper.py
sic_framework/devices/common_desktop/__init__.py
sic_framework/devices/common_desktop/desktop_camera.py
sic_framework/devices/common_desktop/desktop_microphone.py
sic_framework/devices/common_desktop/desktop_spacemouse.py
sic_framework/devices/common_desktop/desktop_speakers.py
sic_framework/devices/common_desktop/desktop_text_to_speech.py
sic_framework/devices/common_franka/__init__.py
sic_framework/devices/common_franka/franka_motion.py
sic_framework/devices/common_franka/franka_motion_recorder.py
sic_framework/devices/common_mini/__init__.py
sic_framework/devices/common_mini/mini_animation.py
sic_framework/devices/common_mini/mini_connector.py
sic_framework/devices/common_mini/mini_microphone.py
sic_framework/devices/common_mini/mini_speaker.py
sic_framework/devices/common_nao_stub/__init__.py
sic_framework/devices/common_nao_stub/nao_stub_autonomous.py
sic_framework/devices/common_nao_stub/nao_stub_buttons.py
sic_framework/devices/common_nao_stub/nao_stub_leds.py
sic_framework/devices/common_nao_stub/nao_stub_motion.py
social_interaction_cloud-2.1.9.dist-info/METADATA
social_interaction_cloud-2.1.9.dist-info/WHEEL
social_interaction_cloud-2.1.9.dist-info/entry_points.txt
social_interaction_cloud-2.1.9.dist-info/top_level.txt
social_interaction_cloud-2.1.9.dist-info/RECORD
